rgn/__init__.py
rgn/rgn.py
rgn-0.1.13.dist-info/LICENSE
rgn-0.1.13.dist-info/METADATA
rgn-0.1.13.dist-info/WHEEL
rgn-0.1.13.dist-info/top_level.txt
rgn-0.1.13.dist-info/RECORD
