Metadata-Version: 2.1
Name: rgn
Version: 0.1.13
Summary: Rank Gaussian Normalization
Home-page: https://github.com/RogerZhangsc/Porto-Seguros-Safe-Driver-Prediction
Author: Roger
Author-email: 
License: UNKNOWN
Platform: UNKNOWN
Classifier: Programming Language :: Python :: 3
Classifier: License :: OSI Approved :: MIT License
Classifier: Operating System :: OS Independent
